nonebot_plugin_zepplife/__init__.py
nonebot_plugin_zepplife/Config.py
nonebot_plugin_zepplife/ResultModule.py
nonebot_plugin_zepplife/Step.py
nonebot_plugin_zepplife/Userdata.py
nonebot_plugin_zepplife-0.1.8.dist-info/LICENSE
nonebot_plugin_zepplife-0.1.8.dist-info/METADATA
nonebot_plugin_zepplife-0.1.8.dist-info/WHEEL
nonebot_plugin_zepplife-0.1.8.dist-info/RECORD
