Metadata-Version: 2.3
Name: nonebot-plugin-zepplife
Version: 0.1.8
Summary: 基于调用xwteam平台专属api运行的机器人插件，目前仅支持Zepp、微信、支付宝刷步，后续还会更新其他功能
Home-page: https://github.com/1296lol/nonebot-plugin-zepplife
Author: 1296
Author-email: hh1296@foxmail.com
Requires-Python: >=3.9,<4.0
Classifier: Programming Language :: Python :: 3
Classifier: Programming Language :: Python :: 3.9
Classifier: Programming Language :: Python :: 3.10
Classifier: Programming Language :: Python :: 3.11
Classifier: Programming Language :: Python :: 3.12
Classifier: Programming Language :: Python :: 3.13
Requires-Dist: aiofiles (>=23.2.1,<24.0.0)
Requires-Dist: httpx (>=0.24.0,<0.25.0)
Requires-Dist: nonebot-adapter-onebot (>=2.2.0,<3.0.0)
Requires-Dist: nonebot2 (>=2.2.0,<3.0.0)
